setup.py
pyfeivalidators/__init__.py
pyfeivalidators/base.py
pyfeivalidators/email.py
pyfeivalidators.egg-info/PKG-INFO
pyfeivalidators.egg-info/SOURCES.txt
pyfeivalidators.egg-info/dependency_links.txt
pyfeivalidators.egg-info/not-zip-safe
pyfeivalidators.egg-info/requires.txt
pyfeivalidators.egg-info/top_level.txt