Metadata-Version: 1.0
Name: pyfeivalidators
Version: 0.0.1
Summary: Common pyfeivalidators component.
Home-page: https://github.com/istommao/pyvalidators
Author: feiger
Author-email: 351275698@qq.com
License: MIT License
Keywords: pyfeivalidators is a common validators component,only testing!
Platform: UNKNOWN
